extras/__init__.py
extras/ephemeris.py
extras/moon.py
extras/sun.py
uvoxid/__init__.py
uvoxid/core.py
uvoxid/corrections.py
uvoxid/formats.py
uvoxid/scale.py
uvoxid-0.1.0.dist-info/licenses/LICENSE
uvoxid-0.1.0.dist-info/METADATA
uvoxid-0.1.0.dist-info/WHEEL
uvoxid-0.1.0.dist-info/top_level.txt
uvoxid-0.1.0.dist-info/RECORD
