Metadata-Version: 2.4
Name: uvoxid
Version: 0.1.0
Summary: Universal Voxel Identifier (UVoxID) — deterministic 192-bit coordinate system for spherical space
Author-email: "Dr. Ippy" <admin@jdplumbingsoflo.com>
License:                                  Apache License
Project-URL: Homepage, https://github.com/JDPlumbing/uvoxid
Project-URL: Repository, https://github.com/JDPlumbing/uvoxid
Project-URL: Issues, https://github.com/JDPlumbing/uvoxid/issues
Project-URL: Changelog, https://github.com/JDPlumbing/uvoxid/releases
Keywords: coordinates,spatial,voxel,physics,geospatial
Classifier: Programming Language :: Python :: 3
Classifier: Programming Language :: Python :: 3.9
Classifier: Programming Language :: Python :: 3.10
Classifier: Programming Language :: Python :: 3.11
Classifier: Programming Language :: Python :: 3.12
Classifier: License :: OSI Approved :: Apache Software License
Classifier: Operating System :: OS Independent
Classifier: Intended Audience :: Science/Research
Classifier: Topic :: Scientific/Engineering
Classifier: Topic :: Software Development :: Libraries :: Python Modules
Requires-Python: >=3.9
License-File: LICENSE
Dynamic: license-file
